MANIFEST.in
README.txt
setup.cfg
setup.py
babble/__init__.py
babble.server.egg-info/PKG-INFO
babble.server.egg-info/SOURCES.txt
babble.server.egg-info/dependency_links.txt
babble.server.egg-info/entry_points.txt
babble.server.egg-info/namespace_packages.txt
babble.server.egg-info/not-zip-safe
babble.server.egg-info/requires.txt
babble.server.egg-info/top_level.txt
babble/server/TODO.txt
babble/server/__init__.py
babble/server/chatroom.py
babble/server/config.py
babble/server/configure.zcml
babble/server/conversation.py
babble/server/interfaces.py
babble/server/message.py
babble/server/messagebox.py
babble/server/service.py
babble/server/user.py
babble/server/utils.py
babble/server/version.txt
babble/server/Extensions/__init__.py
babble/server/Extensions/upgrade_to_1_0.py
babble/server/browser/__init__.py
babble/server/browser/addChatService.pt
babble/server/browser/configure.zcml
babble/server/browser/service.png
babble/server/browser/service.py
babble/server/stresstests/__init__.py
babble/server/stresstests/stresstestMultiThread.py
babble/server/tests/__init__.py
babble/server/tests/stress_test.py
babble/server/tests/test_chatservice.py
docs/CHANGES.txt
docs/CONTRIBUTORS.txt
docs/INSTALL.txt
docs/LICENSE.GPL