Metadata-Version: 1.0
Name: babble.server
Version: 1.1
Summary: A backend messaging server for Zope2.
Home-page: http://svn.plone.org/svn/plone/plone.example
Author: JC Brand
Author-email: jc@opkode.com
License: GPL
Keywords: chat zope plone
Platform: UNKNOWN
Classifier: Programming Language :: Python
Classifier: Framework :: Zope2
